cyclarity_in_vehicle_sdk/__init__.py
cyclarity_in_vehicle_sdk/background_process/README.md
cyclarity_in_vehicle_sdk/background_process/__init__.py
cyclarity_in_vehicle_sdk/background_process/base_background_process.py
cyclarity_in_vehicle_sdk/background_process/base_background_process_controller.py
cyclarity_in_vehicle_sdk/background_process/base_rpyc_service.py
cyclarity_in_vehicle_sdk/background_process/process_handle.py
cyclarity_in_vehicle_sdk/communication/__init__.py
cyclarity_in_vehicle_sdk/communication/base/communicator_base.py
cyclarity_in_vehicle_sdk/communication/can/base/can_communicator_base.py
cyclarity_in_vehicle_sdk/communication/can/impl/can_communicator_socketcan.py
cyclarity_in_vehicle_sdk/communication/doip/doip_communicator.py
cyclarity_in_vehicle_sdk/communication/ip/base/ip_communicator_base.py
cyclarity_in_vehicle_sdk/communication/ip/base/raw_socket_base.py
cyclarity_in_vehicle_sdk/communication/ip/models/ip_models.py
cyclarity_in_vehicle_sdk/communication/ip/raw/raw_socket.py
cyclarity_in_vehicle_sdk/communication/ip/tcp/tcp.py
cyclarity_in_vehicle_sdk/communication/ip/udp/multicast.py
cyclarity_in_vehicle_sdk/communication/ip/udp/udp.py
cyclarity_in_vehicle_sdk/communication/isotp/base/isotp_communicator_base.py
cyclarity_in_vehicle_sdk/communication/isotp/impl/isotp_communicator.py
cyclarity_in_vehicle_sdk/communication/wlan/crypto_utils.py
cyclarity_in_vehicle_sdk/communication/wlan/mac_parsing.py
cyclarity_in_vehicle_sdk/communication/wlan/radiotap_prasing.py
cyclarity_in_vehicle_sdk/communication/wlan/types.py
cyclarity_in_vehicle_sdk/communication/wlan/wlan_communicator.py
cyclarity_in_vehicle_sdk/configuration_manager/__init__.py
cyclarity_in_vehicle_sdk/configuration_manager/actions.py
cyclarity_in_vehicle_sdk/configuration_manager/configuration_manager.py
cyclarity_in_vehicle_sdk/configuration_manager/models.py
cyclarity_in_vehicle_sdk/external/__init__.py
cyclarity_in_vehicle_sdk/external/python_radiotap/.gitignore
cyclarity_in_vehicle_sdk-1.1.7.dist-info/LICENCE
cyclarity_in_vehicle_sdk-1.1.7.dist-info/METADATA
cyclarity_in_vehicle_sdk-1.1.7.dist-info/WHEEL
cyclarity_in_vehicle_sdk-1.1.7.dist-info/RECORD
