Metadata-Version: 2.3
Name: cyclarity-in-vehicle-sdk
Version: 1.1.7
Summary: 
Author: Cymotive
Author-email: clarity@cymotive.com
Requires-Python: >=3.10,<4.0
Classifier: Programming Language :: Python :: 3
Classifier: Programming Language :: Python :: 3.10
Classifier: Programming Language :: Python :: 3.11
Classifier: Programming Language :: Python :: 3.12
Classifier: Programming Language :: Python :: 3.13
Requires-Dist: adb-shell (>=0.4.4,<0.5.0)
Requires-Dist: can-isotp (>=2.0.6,<3.0.0)
Requires-Dist: cmake (>=3.30.2,<4.0.0)
Requires-Dist: construct (>=2.10.70,<3.0.0)
Requires-Dist: cryptography (>=44.0.2,<45.0.0)
Requires-Dist: cyclarity-sdk (>=1.0.91,<2.0.0)
Requires-Dist: doipclient (>=1.1.1,<2.0.0)
Requires-Dist: gpiod (>=2.2.3,<3.0.0)
Requires-Dist: jsonargparse (>=4.34.0,<4.35.0)
Requires-Dist: nmcli (==1.5.0)
Requires-Dist: paramiko (>=3.4.1,<4.0.0)
Requires-Dist: py-pcapplusplus (>=1.0.10,<2.0.0)
Requires-Dist: pycryptodome (>=3.21.0,<4.0.0)
Requires-Dist: pyroute2 (==0.8.1)
Requires-Dist: pyserial (>=3.5,<4.0)
Requires-Dist: python-can
Requires-Dist: rpyc (>=6.0.2,<7.0.0)
Requires-Dist: udsoncan (>=1.23.1,<2.0.0)
